{"ballerinax/github:0.99.12:User":{"id":"int","login":"string","url":"string","avatar_url":"string","node_id":"string","gravatar_id":"string","html_url":"string","followers_url":"string","following_url":"string","gists_url":"string","starred_url":"string","subscriptions_url":"string","organizations_url":"string","repos_url":"string","events_url":"string","received_events_url":"string","type":"string","site_admin":"boolean","name":"string?","company":"string?","blog":"string","location":"string?","email":"string?","hireable":"boolean?","bio":"string?","twitter_username":"string?","public_repos":"int","public_gists":"int","followers":"int","following":"int","created_at":"string","updated_at":"string","private_gists":"int","total_private_repos":"int","owned_private_repos":"int","disk_usage":"int","collaborators":"int","two_factor_authentication":"boolean","plan":"ballerinax/github:0.99.12:Plan"}}